vidscaler/__init__.py
vidscaler/__main__.py
vidscaler/gui.py
vidscaler-2024.4.15.dist-info/METADATA
vidscaler-2024.4.15.dist-info/WHEEL
vidscaler-2024.4.15.dist-info/entry_points.txt
vidscaler-2024.4.15.dist-info/licenses/LICENSE
vidscaler-2024.4.15.dist-info/RECORD
