Metadata-Version: 2.3
Name: vidscaler
Version: 2024.4.15
Project-URL: Homepage, https://github.com/nbdy/vidscaler
Project-URL: Documentation, https://github.com/nbdy/vidscaler/wiki
Project-URL: Repository, https://github.com/nbdy/vidscaler.git
Project-URL: Issues, https://github.com/nbdy/vidscaler/issues
Project-URL: Changelog, https://github.com/nbdy/vidscaler/blob/main/CHANGELOG.md
Author: nbdy
Maintainer: nbdy
License: MIT License
License-File: LICENSE
Keywords: esrgan,gui,realesrgan,upscaling,video upscaler
Classifier: Development Status :: 4 - Beta
Classifier: License :: OSI Approved :: MIT License
Classifier: Programming Language :: Python :: 3.11
Classifier: Programming Language :: Python :: 3.12
Requires-Python: >=3.11
Requires-Dist: customtkinter
Requires-Dist: loguru
Requires-Dist: moviepy
Requires-Dist: numpy
Requires-Dist: opencv-python
Requires-Dist: py-real-esrgan
Requires-Dist: tqdm
